COPYRIGHT
MANIFEST.in
Makefile
README
setup.py
test/__init__.py
test/__init__.pyc
test/test_compile.py
test/test_example.py
test/__pycache__/test_compile.cpython-27-PYTEST.pyc
test/__pycache__/test_example.cpython-27-PYTEST.pyc
tiddlywebplugins/__init__.py
tiddlywebplugins/jsonp.py
tiddlywebplugins.jsonp.egg-info/PKG-INFO
tiddlywebplugins.jsonp.egg-info/SOURCES.txt
tiddlywebplugins.jsonp.egg-info/dependency_links.txt
tiddlywebplugins.jsonp.egg-info/namespace_packages.txt
tiddlywebplugins.jsonp.egg-info/not-zip-safe
tiddlywebplugins.jsonp.egg-info/requires.txt
tiddlywebplugins.jsonp.egg-info/top_level.txt