Metadata-Version: 1.0
Name: tiddlywebplugins.jsonp
Version: 0.7
Summary: JSONP serialization for TiddlyWeb
Home-page: http://pypi.python.org/pypi/tiddlywebplugins.jsonp
Author: Chris Dent
Author-email: cdent@peermore.com
License: BSD
Platform: Posix; MacOS X; Windows
